colours_cli
