Metadata-Version: 1.0
Name: colours-cli
Version: 0.6.0
Summary: CLI using colours_library
Home-page: https://gitlab.bitcomp.intra/eryk_malczyk/colourscli
Author: ErykMalczyk
Author-email: eryk.malczyk@bitcomp.fi
License: some_licence
Platform: UNKNOWN
